artof/__init__.py
artof/artof_loader.py
artof/artof_utils.py
artof/base_loader.py
artof/data_process.py
artof/data_read.py
artof/default_bin_config.py
artof/live_loader.py
artof/log_utils.py
artof/nexus_export.py
artof/normalize.py
artof/plotting.py
artof/pump_probe_loader.py
artof/sweep.py
artof/threading_utils.py
artof/transform.py
artof/eln_base/__init__.py
artof/eln_base/mpes.base.yaml
artof-1.2.1.dist-info/licenses/LICENSE
artof-1.2.1.dist-info/METADATA
artof-1.2.1.dist-info/WHEEL
artof-1.2.1.dist-info/top_level.txt
artof-1.2.1.dist-info/RECORD
