Metadata-Version: 2.4
Name: artof
Version: 1.2.1
Summary: The ARTOF is a tool to read, process and analyze data collected from angle resolved time of flight (ARToF) electron analyzer.
Home-page: https://codebase.helmholtz.cloud/carl.meier/artof
Author: Carl Magnus Meier
Author-email: magnus.meier@helmholtz-berlin.de
Classifier: Programming Language :: Python :: 3
Classifier: License :: OSI Approved :: MIT License
Classifier: Operating System :: OS Independent
Requires-Python: >=3.10
License-File: LICENSE
Requires-Dist: numpy
Requires-Dist: scipy
Requires-Dist: pandas
Requires-Dist: IPython
Requires-Dist: plotly
Requires-Dist: anywidget
Requires-Dist: h5py
Requires-Dist: pyyaml
Provides-Extra: dev
Requires-Dist: pytest; extra == "dev"
Requires-Dist: pytest-cov; extra == "dev"
Dynamic: license-file
